odoo/addons/hr_employee_birth_name/README.rst
odoo/addons/hr_employee_birth_name/__init__.py
odoo/addons/hr_employee_birth_name/__manifest__.py
odoo/addons/hr_employee_birth_name/i18n/ar.po
odoo/addons/hr_employee_birth_name/i18n/cs_CZ.po
odoo/addons/hr_employee_birth_name/i18n/de.po
odoo/addons/hr_employee_birth_name/i18n/es.po
odoo/addons/hr_employee_birth_name/i18n/fi.po
odoo/addons/hr_employee_birth_name/i18n/fr.po
odoo/addons/hr_employee_birth_name/i18n/hr.po
odoo/addons/hr_employee_birth_name/i18n/hr_HR.po
odoo/addons/hr_employee_birth_name/i18n/hr_employee_birth_name.pot
odoo/addons/hr_employee_birth_name/i18n/it.po
odoo/addons/hr_employee_birth_name/i18n/lt.po
odoo/addons/hr_employee_birth_name/i18n/nl_NL.po
odoo/addons/hr_employee_birth_name/i18n/pt_BR.po
odoo/addons/hr_employee_birth_name/i18n/ro.po
odoo/addons/hr_employee_birth_name/i18n/sl.po
odoo/addons/hr_employee_birth_name/models/__init__.py
odoo/addons/hr_employee_birth_name/models/hr_employee.py
odoo/addons/hr_employee_birth_name/static/description/icon.png
odoo/addons/hr_employee_birth_name/views/hr_employee_view.xml
odoo11_addon_hr_employee_birth_name-11.0.1.0.0.99.dev4.dist-info/METADATA
odoo11_addon_hr_employee_birth_name-11.0.1.0.0.99.dev4.dist-info/WHEEL
odoo11_addon_hr_employee_birth_name-11.0.1.0.0.99.dev4.dist-info/top_level.txt
odoo11_addon_hr_employee_birth_name-11.0.1.0.0.99.dev4.dist-info/RECORD
